{"cameraMode":{"drawMode":0,"name":"Shaded","section":"Shading Mode"},"sceneLighting":false,"audioPlay":false,"sceneViewState":{"showFog":true,"showMaterialUpdate":false,"showSkybox":false,"showFlares":true,"showImageEffects":true,"showParticleSystems":true,"showVisualEffectGraphs":true,"m_FxEnabled":true},"in2DMode":false,"pivot":{"x":522.4443359375,"y":357.83966064453127,"z":2.057647705078125},"rotation":{"x":-0.022821256890892984,"y":0.004724262747913599,"z":0.0025125204119831325,"w":-1.0000933408737183},"size":219.3668212890625,"orthographic":false}