{"cameraMode":{"drawMode":0,"name":"Shaded","section":"Shading Mode"},"sceneLighting":true,"audioPlay":false,"sceneViewState":{"showFog":true,"showMaterialUpdate":false,"showSkybox":true,"showFlares":true,"showImageEffects":true,"showParticleSystems":true,"showVisualEffectGraphs":true,"m_FxEnabled":true},"in2DMode":false,"pivot":{"x":-45.67261505126953,"y":-18.49114990234375,"z":22.33734130859375},"rotation":{"x":-0.2115592509508133,"y":0.03689469397068024,"z":-0.008134178817272187,"w":-0.9767179489135742},"size":82.16381072998047,"orthographic":false}